pybackpack/__init__.py
pybackpack/commands.py
pybackpack/cryptography/__init__.py
pybackpack/cryptography/secrets.py
pybackpack/datastores/__init__.py
pybackpack/datastores/mongo.py
pybackpack/datastores/redis.py
pybackpack/os/__init__.py
pybackpack/os/core.py
pybackpack/os/shell.py
pybackpack/text/__init__.py
pybackpack/text/template.py
pybackpack/utils/__init__.py
pybackpack-0.3.1.dist-info/LICENSE
pybackpack-0.3.1.dist-info/METADATA
pybackpack-0.3.1.dist-info/WHEEL
pybackpack-0.3.1.dist-info/top_level.txt
pybackpack-0.3.1.dist-info/RECORD
